wovodat/__init__.py
wovodat/const.py
wovodat/utils.py
wovodat/validator.py
wovodat/wovodat.py
wovodat-0.0.5.dist-info/licenses/LICENSE
wovodat-0.0.5.dist-info/WHEEL
wovodat-0.0.5.dist-info/METADATA
wovodat-0.0.5.dist-info/RECORD
