Metadata-Version: 2.4
Name: wovodat
Version: 0.0.5
Summary: Unofficial WOVOdat python package. WOVOdat is a comprehensive global database on volcanic unrest.
Keywords: wovodat,volcano,data,observatory,volcanoes,volcanic,unrest,forecast
Author-email: Martanto <martanto@live.com>
Requires-Python: >=3.10
Classifier: License :: OSI Approved :: MIT License
Classifier: Operating System :: OS Independent
Classifier: Programming Language :: Python :: 3.10
Classifier: Programming Language :: Python :: 3.11
Classifier: Programming Language :: Python :: 3.12
License-File: LICENSE
Requires-Dist: openpyxl>=3.1.5
Requires-Dist: pandas>=2.2.2
Requires-Dist: openpyxl ; extra == "base"
Requires-Dist: pandas ; extra == "base"
Project-URL: Homepage, https://github.com/martanto/wovodat-python
Project-URL: Issues, https://github.com/martanto/wovodat-python/issues
Provides-Extra: base
